fixparser/__init__.py
fixparser/_version.py
fixparser/exporters.py
fixparser/main.py
fixparser/parser.py
fixparser/dicts/FIX44.xml
fixparser/dicts/FIX50SP2.xml
fixparser/dicts/FIXT11.xml
fixparser/templates/ui.html
fixtranslator-0.1.2.dist-info/licenses/LICENSE
fixtranslator-0.1.2.dist-info/METADATA
fixtranslator-0.1.2.dist-info/WHEEL
fixtranslator-0.1.2.dist-info/top_level.txt
fixtranslator-0.1.2.dist-info/RECORD
