Metadata-Version: 2.4
Name: fixtranslator
Version: 0.1.2
Summary: FIX protocol translator — parse FIX logs to human-readable JSON and forward to logging platforms.
Author-email: Franco Manna <manna.franco@gmail.com>
License: Apache-2.0
Project-URL: Homepage, https://github.com/Terrenus/FIXTranslator
Project-URL: Repository, https://github.com/Terrenus/FIXTranslator
Keywords: fix,financial,parser,splunk,datadog
Classifier: Development Status :: 4 - Beta
Classifier: Intended Audience :: Developers
Classifier: License :: OSI Approved :: Apache Software License
Classifier: Programming Language :: Python :: 3
Classifier: Programming Language :: Python :: 3.11
Requires-Python: >=3.9
License-File: LICENSE
Dynamic: license-file
